MANIFEST.in
fbcore.py
release.py
setup.cfg
setup.py
docs/.buildinfo
docs/genindex.html
docs/index.html
docs/modindex.html
docs/objects.inv
docs/pwc-commands.html
docs/pwc-options.html
docs/python-objects.html
docs/search.html
docs/searchindex.js
docs/sql-support.html
docs/_sources/index.txt
docs/_sources/pwc-commands.txt
docs/_sources/pwc-options.txt
docs/_sources/python-objects.txt
docs/_sources/sql-support.txt
docs/_static/basic.css
docs/_static/default.css
docs/_static/doctools.js
docs/_static/file.png
docs/_static/jquery.js
docs/_static/minus.png
docs/_static/plus.png
docs/_static/pygments.css
docs/_static/searchtools.js
pwc/__init__.py
pwc/fbcmd.py
pwcfb.egg-info/PKG-INFO
pwcfb.egg-info/SOURCES.txt
pwcfb.egg-info/dependency_links.txt
pwcfb.egg-info/entry_points.txt
pwcfb.egg-info/namespace_packages.txt
pwcfb.egg-info/requires.txt
pwcfb.egg-info/top_level.txt