Metadata-Version: 1.0
Name: pwcfb
Version: 0.9.2
Summary: Extensive package that enables PowerConsole to work with Firebird databases.
Home-page: http://www.ibphoenix.cz/pwc/
Author: Pavel Cisar
Author-email: pcisar@users.sourceforge.net
License: IDPL 1.0
Download-URL: http://ibphoenix.cz/pwc/download/
Platform: UNKNOWN
Classifier: Development Status :: 4 - Beta
Classifier: Operating System :: OS Independent
Classifier: Programming Language :: Python
Classifier: Topic :: Software Development :: Libraries :: Python Modules
